draggable_charts/__init__.py
draggable_charts/frontend/build/asset-manifest.json
draggable_charts/frontend/build/bootstrap.min.css
draggable_charts/frontend/build/index.html
draggable_charts/frontend/build/static/js/main.5227bcd4.js
draggable_charts/frontend/build/static/js/main.5227bcd4.js.LICENSE.txt
draggable_charts/frontend/build/static/js/main.5227bcd4.js.map
draggable_charts/frontend/build/static/js/main.e4bdeb00.js
draggable_charts/frontend/build/static/js/main.e4bdeb00.js.LICENSE.txt
draggable_charts/frontend/build/static/js/main.e4bdeb00.js.map
draggable_charts/utils/__init__.py
draggable_charts/utils/callback.py
draggable_charts/utils/component_func.py
draggable_charts/utils/data_validation.py
draggable_charts/utils/options.py
draggable_charts/widgets/__init__.py
draggable_charts/widgets/bezierchart.py
draggable_charts/widgets/cubicbezierchart.py
draggable_charts/widgets/linechart.py
draggable_charts/widgets/scatterchart.py
draggable_charts-1.2.12.dist-info/LICENSE
draggable_charts-1.2.12.dist-info/METADATA
draggable_charts-1.2.12.dist-info/WHEEL
draggable_charts-1.2.12.dist-info/top_level.txt
draggable_charts-1.2.12.dist-info/RECORD
