Metadata-Version: 2.1
Name: draggable-charts
Version: 1.2.12
Summary: A Streamlit component library for interactive charts in chartjs. Draggable line, scatter, and bezier charts. The updated data of the chart is returned after user interaction.
Home-page: https://github.com/balexandermunoz/draggable-charts
Author: Brayan Munoz
Author-email: balexander.munoz@udea.edu.co
Requires-Python: >=3.7
License-File: LICENSE
Requires-Dist: streamlit >=0.63
Requires-Dist: bezier-interpolation >=0.0.2
Provides-Extra: devel
Requires-Dist: wheel ; extra == 'devel'
Requires-Dist: pytest ==7.4.0 ; extra == 'devel'
Requires-Dist: playwright ==1.39.0 ; extra == 'devel'
Requires-Dist: requests ==2.31.0 ; extra == 'devel'
Requires-Dist: pytest-playwright-snapshot ==1.0 ; extra == 'devel'
Requires-Dist: pytest-rerunfailures ==12.0 ; extra == 'devel'
